README.md
setup.py
disttools/__init__.py
disttools.egg-info/PKG-INFO
disttools.egg-info/SOURCES.txt
disttools.egg-info/dependency_links.txt
disttools.egg-info/not-zip-safe
disttools.egg-info/top_level.txt