Metadata-Version: 1.0
Name: disttools
Version: 0.1.8
Summary: release distribution tools
Home-page: http://github.com/jeppeter/disttools
Author: jeppeter Wang
Author-email: jeppeter@gmail.com
License: MIT
Platform: UNKNOWN
